ntnx_prism_py_client/__init__.py
ntnx_prism_py_client/api_client.py
ntnx_prism_py_client/api_response.py
ntnx_prism_py_client/configuration.py
ntnx_prism_py_client/custom_retry.py
ntnx_prism_py_client/rest.py
ntnx_prism_py_client/api/__init__.py
ntnx_prism_py_client/api/batches_api.py
ntnx_prism_py_client/api/categories_api.py
ntnx_prism_py_client/api/domain_manager_api.py
ntnx_prism_py_client/api/domain_manager_backups_api.py
ntnx_prism_py_client/api/external_storages_api.py
ntnx_prism_py_client/api/registration_api.py
ntnx_prism_py_client/api/tasks_api.py
ntnx_prism_py_client/models/__init__.py
ntnx_prism_py_client/models/OneOfcommon/__init__.py
ntnx_prism_py_client/models/OneOfcommon/v1/__init__.py
ntnx_prism_py_client/models/OneOfcommon/v1/config/KVPairvalue.py
ntnx_prism_py_client/models/OneOfcommon/v1/config/__init__.py
ntnx_prism_py_client/models/OneOfprism/__init__.py
ntnx_prism_py_client/models/OneOfprism/v4/__init__.py
ntnx_prism_py_client/models/OneOfprism/v4/config/CancelTaskApiResponsedata.py
ntnx_prism_py_client/models/OneOfprism/v4/config/CreateCategoryApiResponsedata.py
ntnx_prism_py_client/models/OneOfprism/v4/config/CreateDomainManagerApiResponsedata.py
ntnx_prism_py_client/models/OneOfprism/v4/config/DeleteCategoryApiResponsedata.py
ntnx_prism_py_client/models/OneOfprism/v4/config/ExternalStorageconfig.py
ntnx_prism_py_client/models/OneOfprism/v4/config/GetCategoryApiResponsedata.py
ntnx_prism_py_client/models/OneOfprism/v4/config/GetDomainManagerApiResponsedata.py
ntnx_prism_py_client/models/OneOfprism/v4/config/GetExternalStorageApiResponsedata.py
ntnx_prism_py_client/models/OneOfprism/v4/config/GetTaskApiResponsedata.py
ntnx_prism_py_client/models/OneOfprism/v4/config/GetTaskJobApiResponsedata.py
ntnx_prism_py_client/models/OneOfprism/v4/config/ListCategoriesApiResponsedata.py
ntnx_prism_py_client/models/OneOfprism/v4/config/ListDomainManagerApiResponsedata.py
ntnx_prism_py_client/models/OneOfprism/v4/config/ListTaskEntitiesApiResponsedata.py
ntnx_prism_py_client-4.2.1.dist-info/LICENSE.txt
ntnx_prism_py_client-4.2.1.dist-info/METADATA
ntnx_prism_py_client-4.2.1.dist-info/WHEEL
ntnx_prism_py_client-4.2.1.dist-info/top_level.txt
ntnx_prism_py_client-4.2.1.dist-info/RECORD
